{
  "language": "Korean (Hanja)",
  "code": "ko-hanja",
  "mode": "character",
  "unitLabel": "characters",
  "maxRank": 10000,
  "bandSize": 500,
  "bands": [
    {
      "index": 1,
      "range": "1-500",
      "size": 500
    },
    {
      "index": 2,
      "range": "501-1000",
      "size": 500
    },
    {
      "index": 3,
      "range": "1001-1500",
      "size": 500
    },
    {
      "index": 4,
      "range": "1501-2000",
      "size": 500
    },
    {
      "index": 5,
      "range": "2001-2500",
      "size": 500
    },
    {
      "index": 6,
      "range": "2501-3000",
      "size": 500
    },
    {
      "index": 7,
      "range": "3001-3500",
      "size": 500
    },
    {
      "index": 8,
      "range": "3501-4000",
      "size": 500
    },
    {
      "index": 9,
      "range": "4001-4500",
      "size": 500
    },
    {
      "index": 10,
      "range": "4501-5000",
      "size": 500
    },
    {
      "index": 11,
      "range": "5001-5500",
      "size": 500
    },
    {
      "index": 12,
      "range": "5501-6000",
      "size": 500
    },
    {
      "index": 13,
      "range": "6001-6500",
      "size": 500
    },
    {
      "index": 14,
      "range": "6501-7000",
      "size": 500
    },
    {
      "index": 15,
      "range": "7001-7500",
      "size": 500
    },
    {
      "index": 16,
      "range": "7501-8000",
      "size": 500
    },
    {
      "index": 17,
      "range": "8001-8500",
      "size": 500
    },
    {
      "index": 18,
      "range": "8501-9000",
      "size": 500
    },
    {
      "index": 19,
      "range": "9001-9500",
      "size": 500
    },
    {
      "index": 20,
      "range": "9501-10000",
      "size": 500
    }
  ],
  "words": [
    {
      "word": "丂",
      "rank": 13,
      "band": 1,
      "range": "1-500"
    },
    {
      "word": "丆",
      "rank": 38,
      "band": 1,
      "range": "1-500"
    },
    {
      "word": "下",
      "rank": 63,
      "band": 1,
      "range": "1-500"
    },
    {
      "word": "丏",
      "rank": 88,
      "band": 1,
      "range": "1-500"
    },
    {
      "word": "且",
      "rank": 113,
      "band": 1,
      "range": "1-500"
    },
    {
      "word": "丘",
      "rank": 138,
      "band": 1,
      "range": "1-500"
    },
    {
      "word": "丝",
      "rank": 163,
      "band": 1,
      "range": "1-500"
    },
    {
      "word": "両",
      "rank": 188,
      "band": 1,
      "range": "1-500"
    },
    {
      "word": "並",
      "rank": 213,
      "band": 1,
      "range": "1-500"
    },
    {
      "word": "个",
      "rank": 238,
      "band": 1,
      "range": "1-500"
    },
    {
      "word": "丯",
      "rank": 263,
      "band": 1,
      "range": "1-500"
    },
    {
      "word": "丳",
      "rank": 288,
      "band": 1,
      "range": "1-500"
    },
    {
      "word": "丸",
      "rank": 313,
      "band": 1,
      "range": "1-500"
    },
    {
      "word": "丼",
      "rank": 338,
      "band": 1,
      "range": "1-500"
    },
    {
      "word": "乁",
      "rank": 363,
      "band": 1,
      "range": "1-500"
    },
    {
      "word": "久",
      "rank": 388,
      "band": 1,
      "range": "1-500"
    },
    {
      "word": "乊",
      "rank": 413,
      "band": 1,
      "range": "1-500"
    },
    {
      "word": "乎",
      "rank": 438,
      "band": 1,
      "range": "1-500"
    },
    {
      "word": "乓",
      "rank": 463,
      "band": 1,
      "range": "1-500"
    },
    {
      "word": "乗",
      "rank": 488,
      "band": 1,
      "range": "1-500"
    },
    {
      "word": "乜",
      "rank": 513,
      "band": 2,
      "range": "501-1000"
    },
    {
      "word": "习",
      "rank": 538,
      "band": 2,
      "range": "501-1000"
    },
    {
      "word": "乥",
      "rank": 563,
      "band": 2,
      "range": "501-1000"
    },
    {
      "word": "乩",
      "rank": 588,
      "band": 2,
      "range": "501-1000"
    },
    {
      "word": "乮",
      "rank": 613,
      "band": 2,
      "range": "501-1000"
    },
    {
      "word": "乲",
      "rank": 638,
      "band": 2,
      "range": "501-1000"
    },
    {
      "word": "乷",
      "rank": 663,
      "band": 2,
      "range": "501-1000"
    },
    {
      "word": "乻",
      "rank": 688,
      "band": 2,
      "range": "501-1000"
    },
    {
      "word": "亀",
      "rank": 713,
      "band": 2,
      "range": "501-1000"
    },
    {
      "word": "亄",
      "rank": 738,
      "band": 2,
      "range": "501-1000"
    },
    {
      "word": "争",
      "rank": 763,
      "band": 2,
      "range": "501-1000"
    },
    {
      "word": "亍",
      "rank": 788,
      "band": 2,
      "range": "501-1000"
    },
    {
      "word": "互",
      "rank": 813,
      "band": 2,
      "range": "501-1000"
    },
    {
      "word": "亖",
      "rank": 838,
      "band": 2,
      "range": "501-1000"
    },
    {
      "word": "些",
      "rank": 863,
      "band": 2,
      "range": "501-1000"
    },
    {
      "word": "亟",
      "rank": 888,
      "band": 2,
      "range": "501-1000"
    },
    {
      "word": "交",
      "rank": 913,
      "band": 2,
      "range": "501-1000"
    },
    {
      "word": "亨",
      "rank": 938,
      "band": 2,
      "range": "501-1000"
    },
    {
      "word": "亭",
      "rank": 963,
      "band": 2,
      "range": "501-1000"
    },
    {
      "word": "亱",
      "rank": 988,
      "band": 2,
      "range": "501-1000"
    },
    {
      "word": "亶",
      "rank": 1013,
      "band": 3,
      "range": "1001-1500"
    },
    {
      "word": "人",
      "rank": 1038,
      "band": 3,
      "range": "1001-1500"
    },
    {
      "word": "亿",
      "rank": 1063,
      "band": 3,
      "range": "1001-1500"
    },
    {
      "word": "仃",
      "rank": 1088,
      "band": 3,
      "range": "1001-1500"
    },
    {
      "word": "仈",
      "rank": 1113,
      "band": 3,
      "range": "1001-1500"
    },
    {
      "word": "仌",
      "rank": 1138,
      "band": 3,
      "range": "1001-1500"
    },
    {
      "word": "仑",
      "rank": 1163,
      "band": 3,
      "range": "1001-1500"
    },
    {
      "word": "仕",
      "rank": 1188,
      "band": 3,
      "range": "1001-1500"
    },
    {
      "word": "仚",
      "rank": 1213,
      "band": 3,
      "range": "1001-1500"
    },
    {
      "word": "仞",
      "rank": 1238,
      "band": 3,
      "range": "1001-1500"
    },
    {
      "word": "代",
      "rank": 1263,
      "band": 3,
      "range": "1001-1500"
    },
    {
      "word": "仧",
      "rank": 1288,
      "band": 3,
      "range": "1001-1500"
    },
    {
      "word": "们",
      "rank": 1313,
      "band": 3,
      "range": "1001-1500"
    },
    {
      "word": "仰",
      "rank": 1338,
      "band": 3,
      "range": "1001-1500"
    },
    {
      "word": "仵",
      "rank": 1363,
      "band": 3,
      "range": "1001-1500"
    },
    {
      "word": "仹",
      "rank": 1388,
      "band": 3,
      "range": "1001-1500"
    },
    {
      "word": "仾",
      "rank": 1413,
      "band": 3,
      "range": "1001-1500"
    },
    {
      "word": "伂",
      "rank": 1438,
      "band": 3,
      "range": "1001-1500"
    },
    {
      "word": "伇",
      "rank": 1463,
      "band": 3,
      "range": "1001-1500"
    },
    {
      "word": "伋",
      "rank": 1488,
      "band": 3,
      "range": "1001-1500"
    },
    {
      "word": "伐",
      "rank": 1513,
      "band": 4,
      "range": "1501-2000"
    },
    {
      "word": "伔",
      "rank": 1538,
      "band": 4,
      "range": "1501-2000"
    },
    {
      "word": "伙",
      "rank": 1563,
      "band": 4,
      "range": "1501-2000"
    },
    {
      "word": "伝",
      "rank": 1588,
      "band": 4,
      "range": "1501-2000"
    },
    {
      "word": "伢",
      "rank": 1613,
      "band": 4,
      "range": "1501-2000"
    },
    {
      "word": "伦",
      "rank": 1638,
      "band": 4,
      "range": "1501-2000"
    },
    {
      "word": "伫",
      "rank": 1663,
      "band": 4,
      "range": "1501-2000"
    },
    {
      "word": "伯",
      "rank": 1688,
      "band": 4,
      "range": "1501-2000"
    },
    {
      "word": "伴",
      "rank": 1713,
      "band": 4,
      "range": "1501-2000"
    },
    {
      "word": "伸",
      "rank": 1738,
      "band": 4,
      "range": "1501-2000"
    },
    {
      "word": "伽",
      "rank": 1763,
      "band": 4,
      "range": "1501-2000"
    },
    {
      "word": "佁",
      "rank": 1788,
      "band": 4,
      "range": "1501-2000"
    },
    {
      "word": "但",
      "rank": 1813,
      "band": 4,
      "range": "1501-2000"
    },
    {
      "word": "佊",
      "rank": 1838,
      "band": 4,
      "range": "1501-2000"
    },
    {
      "word": "住",
      "rank": 1863,
      "band": 4,
      "range": "1501-2000"
    },
    {
      "word": "体",
      "rank": 1888,
      "band": 4,
      "range": "1501-2000"
    },
    {
      "word": "佘",
      "rank": 1913,
      "band": 4,
      "range": "1501-2000"
    },
    {
      "word": "作",
      "rank": 1938,
      "band": 4,
      "range": "1501-2000"
    },
    {
      "word": "佡",
      "rank": 1963,
      "band": 4,
      "range": "1501-2000"
    },
    {
      "word": "佥",
      "rank": 1988,
      "band": 4,
      "range": "1501-2000"
    },
    {
      "word": "佪",
      "rank": 2013,
      "band": 5,
      "range": "2001-2500"
    },
    {
      "word": "佮",
      "rank": 2038,
      "band": 5,
      "range": "2001-2500"
    },
    {
      "word": "佳",
      "rank": 2063,
      "band": 5,
      "range": "2001-2500"
    },
    {
      "word": "佷",
      "rank": 2088,
      "band": 5,
      "range": "2001-2500"
    },
    {
      "word": "佼",
      "rank": 2113,
      "band": 5,
      "range": "2001-2500"
    },
    {
      "word": "侀",
      "rank": 2138,
      "band": 5,
      "range": "2001-2500"
    },
    {
      "word": "侅",
      "rank": 2163,
      "band": 5,
      "range": "2001-2500"
    },
    {
      "word": "侉",
      "rank": 2188,
      "band": 5,
      "range": "2001-2500"
    },
    {
      "word": "侎",
      "rank": 2213,
      "band": 5,
      "range": "2001-2500"
    },
    {
      "word": "侒",
      "rank": 2238,
      "band": 5,
      "range": "2001-2500"
    },
    {
      "word": "侗",
      "rank": 2263,
      "band": 5,
      "range": "2001-2500"
    },
    {
      "word": "供",
      "rank": 2288,
      "band": 5,
      "range": "2001-2500"
    },
    {
      "word": "侠",
      "rank": 2313,
      "band": 5,
      "range": "2001-2500"
    },
    {
      "word": "侤",
      "rank": 2338,
      "band": 5,
      "range": "2001-2500"
    },
    {
      "word": "侩",
      "rank": 2363,
      "band": 5,
      "range": "2001-2500"
    },
    {
      "word": "侭",
      "rank": 2388,
      "band": 5,
      "range": "2001-2500"
    },
    {
      "word": "侲",
      "rank": 2413,
      "band": 5,
      "range": "2001-2500"
    },
    {
      "word": "侶",
      "rank": 2438,
      "band": 5,
      "range": "2001-2500"
    },
    {
      "word": "侻",
      "rank": 2463,
      "band": 5,
      "range": "2001-2500"
    },
    {
      "word": "便",
      "rank": 2488,
      "band": 5,
      "range": "2001-2500"
    },
    {
      "word": "俄",
      "rank": 2513,
      "band": 6,
      "range": "2501-3000"
    },
    {
      "word": "俈",
      "rank": 2538,
      "band": 6,
      "range": "2501-3000"
    },
    {
      "word": "俍",
      "rank": 2563,
      "band": 6,
      "range": "2501-3000"
    },
    {
      "word": "俑",
      "rank": 2588,
      "band": 6,
      "range": "2501-3000"
    },
    {
      "word": "俖",
      "rank": 2613,
      "band": 6,
      "range": "2501-3000"
    },
    {
      "word": "俚",
      "rank": 2638,
      "band": 6,
      "range": "2501-3000"
    },
    {
      "word": "俟",
      "rank": 2663,
      "band": 6,
      "range": "2501-3000"
    },
    {
      "word": "俣",
      "rank": 2688,
      "band": 6,
      "range": "2501-3000"
    },
    {
      "word": "俨",
      "rank": 2713,
      "band": 6,
      "range": "2501-3000"
    },
    {
      "word": "俬",
      "rank": 2738,
      "band": 6,
      "range": "2501-3000"
    },
    {
      "word": "俱",
      "rank": 2763,
      "band": 6,
      "range": "2501-3000"
    },
    {
      "word": "俵",
      "rank": 2788,
      "band": 6,
      "range": "2501-3000"
    },
    {
      "word": "俺",
      "rank": 2813,
      "band": 6,
      "range": "2501-3000"
    },
    {
      "word": "俾",
      "rank": 2838,
      "band": 6,
      "range": "2501-3000"
    },
    {
      "word": "倃",
      "rank": 2863,
      "band": 6,
      "range": "2501-3000"
    },
    {
      "word": "倇",
      "rank": 2888,
      "band": 6,
      "range": "2501-3000"
    },
    {
      "word": "倌",
      "rank": 2913,
      "band": 6,
      "range": "2501-3000"
    },
    {
      "word": "倐",
      "rank": 2938,
      "band": 6,
      "range": "2501-3000"
    },
    {
      "word": "倕",
      "rank": 2963,
      "band": 6,
      "range": "2501-3000"
    },
    {
      "word": "候",
      "rank": 2988,
      "band": 6,
      "range": "2501-3000"
    },
    {
      "word": "倞",
      "rank": 3013,
      "band": 7,
      "range": "3001-3500"
    },
    {
      "word": "倢",
      "rank": 3038,
      "band": 7,
      "range": "3001-3500"
    },
    {
      "word": "倧",
      "rank": 3063,
      "band": 7,
      "range": "3001-3500"
    },
    {
      "word": "倫",
      "rank": 3088,
      "band": 7,
      "range": "3001-3500"
    },
    {
      "word": "倰",
      "rank": 3113,
      "band": 7,
      "range": "3001-3500"
    },
    {
      "word": "倴",
      "rank": 3138,
      "band": 7,
      "range": "3001-3500"
    },
    {
      "word": "倹",
      "rank": 3163,
      "band": 7,
      "range": "3001-3500"
    },
    {
      "word": "倽",
      "rank": 3188,
      "band": 7,
      "range": "3001-3500"
    },
    {
      "word": "偂",
      "rank": 3213,
      "band": 7,
      "range": "3001-3500"
    },
    {
      "word": "偆",
      "rank": 3238,
      "band": 7,
      "range": "3001-3500"
    },
    {
      "word": "偋",
      "rank": 3263,
      "band": 7,
      "range": "3001-3500"
    },
    {
      "word": "偏",
      "rank": 3288,
      "band": 7,
      "range": "3001-3500"
    },
    {
      "word": "偔",
      "rank": 3313,
      "band": 7,
      "range": "3001-3500"
    },
    {
      "word": "偘",
      "rank": 3338,
      "band": 7,
      "range": "3001-3500"
    },
    {
      "word": "偝",
      "rank": 3363,
      "band": 7,
      "range": "3001-3500"
    },
    {
      "word": "偡",
      "rank": 3388,
      "band": 7,
      "range": "3001-3500"
    },
    {
      "word": "偦",
      "rank": 3413,
      "band": 7,
      "range": "3001-3500"
    },
    {
      "word": "偪",
      "rank": 3438,
      "band": 7,
      "range": "3001-3500"
    },
    {
      "word": "偯",
      "rank": 3463,
      "band": 7,
      "range": "3001-3500"
    },
    {
      "word": "偳",
      "rank": 3488,
      "band": 7,
      "range": "3001-3500"
    },
    {
      "word": "偸",
      "rank": 3513,
      "band": 8,
      "range": "3501-4000"
    },
    {
      "word": "偼",
      "rank": 3538,
      "band": 8,
      "range": "3501-4000"
    },
    {
      "word": "傁",
      "rank": 3563,
      "band": 8,
      "range": "3501-4000"
    },
    {
      "word": "傅",
      "rank": 3588,
      "band": 8,
      "range": "3501-4000"
    },
    {
      "word": "傊",
      "rank": 3613,
      "band": 8,
      "range": "3501-4000"
    },
    {
      "word": "傎",
      "rank": 3638,
      "band": 8,
      "range": "3501-4000"
    },
    {
      "word": "傓",
      "rank": 3663,
      "band": 8,
      "range": "3501-4000"
    },
    {
      "word": "傗",
      "rank": 3688,
      "band": 8,
      "range": "3501-4000"
    },
    {
      "word": "傜",
      "rank": 3713,
      "band": 8,
      "range": "3501-4000"
    },
    {
      "word": "傠",
      "rank": 3738,
      "band": 8,
      "range": "3501-4000"
    },
    {
      "word": "傥",
      "rank": 3763,
      "band": 8,
      "range": "3501-4000"
    },
    {
      "word": "傩",
      "rank": 3788,
      "band": 8,
      "range": "3501-4000"
    },
    {
      "word": "傮",
      "rank": 3813,
      "band": 8,
      "range": "3501-4000"
    },
    {
      "word": "傲",
      "rank": 3838,
      "band": 8,
      "range": "3501-4000"
    },
    {
      "word": "傷",
      "rank": 3863,
      "band": 8,
      "range": "3501-4000"
    },
    {
      "word": "傻",
      "rank": 3888,
      "band": 8,
      "range": "3501-4000"
    },
    {
      "word": "僀",
      "rank": 3913,
      "band": 8,
      "range": "3501-4000"
    },
    {
      "word": "僄",
      "rank": 3938,
      "band": 8,
      "range": "3501-4000"
    },
    {
      "word": "僉",
      "rank": 3963,
      "band": 8,
      "range": "3501-4000"
    },
    {
      "word": "働",
      "rank": 3988,
      "band": 8,
      "range": "3501-4000"
    },
    {
      "word": "僒",
      "rank": 4013,
      "band": 9,
      "range": "4001-4500"
    },
    {
      "word": "僖",
      "rank": 4038,
      "band": 9,
      "range": "4001-4500"
    },
    {
      "word": "僛",
      "rank": 4063,
      "band": 9,
      "range": "4001-4500"
    },
    {
      "word": "僟",
      "rank": 4088,
      "band": 9,
      "range": "4001-4500"
    },
    {
      "word": "僤",
      "rank": 4113,
      "band": 9,
      "range": "4001-4500"
    },
    {
      "word": "僨",
      "rank": 4138,
      "band": 9,
      "range": "4001-4500"
    },
    {
      "word": "僭",
      "rank": 4163,
      "band": 9,
      "range": "4001-4500"
    },
    {
      "word": "僱",
      "rank": 4188,
      "band": 9,
      "range": "4001-4500"
    },
    {
      "word": "僶",
      "rank": 4213,
      "band": 9,
      "range": "4001-4500"
    },
    {
      "word": "僺",
      "rank": 4238,
      "band": 9,
      "range": "4001-4500"
    },
    {
      "word": "僿",
      "rank": 4263,
      "band": 9,
      "range": "4001-4500"
    },
    {
      "word": "儃",
      "rank": 4288,
      "band": 9,
      "range": "4001-4500"
    },
    {
      "word": "儈",
      "rank": 4313,
      "band": 9,
      "range": "4001-4500"
    },
    {
      "word": "儌",
      "rank": 4338,
      "band": 9,
      "range": "4001-4500"
    },
    {
      "word": "儑",
      "rank": 4363,
      "band": 9,
      "range": "4001-4500"
    },
    {
      "word": "儕",
      "rank": 4388,
      "band": 9,
      "range": "4001-4500"
    },
    {
      "word": "儚",
      "rank": 4413,
      "band": 9,
      "range": "4001-4500"
    },
    {
      "word": "儞",
      "rank": 4438,
      "band": 9,
      "range": "4001-4500"
    },
    {
      "word": "儣",
      "rank": 4463,
      "band": 9,
      "range": "4001-4500"
    },
    {
      "word": "儧",
      "rank": 4488,
      "band": 9,
      "range": "4001-4500"
    },
    {
      "word": "儬",
      "rank": 4513,
      "band": 10,
      "range": "4501-5000"
    },
    {
      "word": "儰",
      "rank": 4538,
      "band": 10,
      "range": "4501-5000"
    },
    {
      "word": "儵",
      "rank": 4563,
      "band": 10,
      "range": "4501-5000"
    },
    {
      "word": "儹",
      "rank": 4588,
      "band": 10,
      "range": "4501-5000"
    },
    {
      "word": "儾",
      "rank": 4613,
      "band": 10,
      "range": "4501-5000"
    },
    {
      "word": "兂",
      "rank": 4638,
      "band": 10,
      "range": "4501-5000"
    },
    {
      "word": "兇",
      "rank": 4663,
      "band": 10,
      "range": "4501-5000"
    },
    {
      "word": "克",
      "rank": 4688,
      "band": 10,
      "range": "4501-5000"
    },
    {
      "word": "児",
      "rank": 4713,
      "band": 10,
      "range": "4501-5000"
    },
    {
      "word": "兔",
      "rank": 4738,
      "band": 10,
      "range": "4501-5000"
    },
    {
      "word": "兙",
      "rank": 4763,
      "band": 10,
      "range": "4501-5000"
    },
    {
      "word": "兝",
      "rank": 4788,
      "band": 10,
      "range": "4501-5000"
    },
    {
      "word": "兢",
      "rank": 4813,
      "band": 10,
      "range": "4501-5000"
    },
    {
      "word": "兦",
      "rank": 4838,
      "band": 10,
      "range": "4501-5000"
    },
    {
      "word": "八",
      "rank": 4863,
      "band": 10,
      "range": "4501-5000"
    },
    {
      "word": "兯",
      "rank": 4888,
      "band": 10,
      "range": "4501-5000"
    },
    {
      "word": "兴",
      "rank": 4913,
      "band": 10,
      "range": "4501-5000"
    },
    {
      "word": "典",
      "rank": 4938,
      "band": 10,
      "range": "4501-5000"
    },
    {
      "word": "兽",
      "rank": 4963,
      "band": 10,
      "range": "4501-5000"
    },
    {
      "word": "冁",
      "rank": 4988,
      "band": 10,
      "range": "4501-5000"
    },
    {
      "word": "円",
      "rank": 5013,
      "band": 11,
      "range": "5001-5500"
    },
    {
      "word": "冊",
      "rank": 5038,
      "band": 11,
      "range": "5001-5500"
    },
    {
      "word": "冏",
      "rank": 5063,
      "band": 11,
      "range": "5001-5500"
    },
    {
      "word": "冓",
      "rank": 5088,
      "band": 11,
      "range": "5001-5500"
    },
    {
      "word": "冘",
      "rank": 5113,
      "band": 11,
      "range": "5001-5500"
    },
    {
      "word": "农",
      "rank": 5138,
      "band": 11,
      "range": "5001-5500"
    },
    {
      "word": "冡",
      "rank": 5163,
      "band": 11,
      "range": "5001-5500"
    },
    {
      "word": "冥",
      "rank": 5188,
      "band": 11,
      "range": "5001-5500"
    },
    {
      "word": "冪",
      "rank": 5213,
      "band": 11,
      "range": "5001-5500"
    },
    {
      "word": "冮",
      "rank": 5238,
      "band": 11,
      "range": "5001-5500"
    },
    {
      "word": "决",
      "rank": 5263,
      "band": 11,
      "range": "5001-5500"
    },
    {
      "word": "冷",
      "rank": 5288,
      "band": 11,
      "range": "5001-5500"
    },
    {
      "word": "冼",
      "rank": 5313,
      "band": 11,
      "range": "5001-5500"
    },
    {
      "word": "净",
      "rank": 5338,
      "band": 11,
      "range": "5001-5500"
    },
    {
      "word": "凅",
      "rank": 5363,
      "band": 11,
      "range": "5001-5500"
    },
    {
      "word": "凉",
      "rank": 5388,
      "band": 11,
      "range": "5001-5500"
    },
    {
      "word": "凎",
      "rank": 5413,
      "band": 11,
      "range": "5001-5500"
    },
    {
      "word": "凒",
      "rank": 5438,
      "band": 11,
      "range": "5001-5500"
    },
    {
      "word": "凗",
      "rank": 5463,
      "band": 11,
      "range": "5001-5500"
    },
    {
      "word": "凛",
      "rank": 5488,
      "band": 11,
      "range": "5001-5500"
    },
    {
      "word": "几",
      "rank": 5513,
      "band": 12,
      "range": "5501-6000"
    },
    {
      "word": "凤",
      "rank": 5538,
      "band": 12,
      "range": "5501-6000"
    },
    {
      "word": "凩",
      "rank": 5563,
      "band": 12,
      "range": "5501-6000"
    },
    {
      "word": "凭",
      "rank": 5588,
      "band": 12,
      "range": "5501-6000"
    },
    {
      "word": "凲",
      "rank": 5613,
      "band": 12,
      "range": "5501-6000"
    },
    {
      "word": "凶",
      "rank": 5638,
      "band": 12,
      "range": "5501-6000"
    },
    {
      "word": "击",
      "rank": 5663,
      "band": 12,
      "range": "5501-6000"
    },
    {
      "word": "凿",
      "rank": 5688,
      "band": 12,
      "range": "5501-6000"
    },
    {
      "word": "刄",
      "rank": 5713,
      "band": 12,
      "range": "5501-6000"
    },
    {
      "word": "刈",
      "rank": 5738,
      "band": 12,
      "range": "5501-6000"
    },
    {
      "word": "刍",
      "rank": 5763,
      "band": 12,
      "range": "5501-6000"
    },
    {
      "word": "刑",
      "rank": 5788,
      "band": 12,
      "range": "5501-6000"
    },
    {
      "word": "刖",
      "rank": 5813,
      "band": 12,
      "range": "5501-6000"
    },
    {
      "word": "刚",
      "rank": 5838,
      "band": 12,
      "range": "5501-6000"
    },
    {
      "word": "刟",
      "rank": 5863,
      "band": 12,
      "range": "5501-6000"
    },
    {
      "word": "刣",
      "rank": 5888,
      "band": 12,
      "range": "5501-6000"
    },
    {
      "word": "刨",
      "rank": 5913,
      "band": 12,
      "range": "5501-6000"
    },
    {
      "word": "刬",
      "rank": 5938,
      "band": 12,
      "range": "5501-6000"
    },
    {
      "word": "刱",
      "rank": 5963,
      "band": 12,
      "range": "5501-6000"
    },
    {
      "word": "刵",
      "rank": 5988,
      "band": 12,
      "range": "5501-6000"
    },
    {
      "word": "刺",
      "rank": 6013,
      "band": 13,
      "range": "6001-6500"
    },
    {
      "word": "刾",
      "rank": 6038,
      "band": 13,
      "range": "6001-6500"
    },
    {
      "word": "剃",
      "rank": 6063,
      "band": 13,
      "range": "6001-6500"
    },
    {
      "word": "則",
      "rank": 6088,
      "band": 13,
      "range": "6001-6500"
    },
    {
      "word": "剌",
      "rank": 6113,
      "band": 13,
      "range": "6001-6500"
    },
    {
      "word": "剐",
      "rank": 6138,
      "band": 13,
      "range": "6001-6500"
    },
    {
      "word": "剕",
      "rank": 6163,
      "band": 13,
      "range": "6001-6500"
    },
    {
      "word": "剙",
      "rank": 6188,
      "band": 13,
      "range": "6001-6500"
    },
    {
      "word": "剞",
      "rank": 6213,
      "band": 13,
      "range": "6001-6500"
    },
    {
      "word": "剢",
      "rank": 6238,
      "band": 13,
      "range": "6001-6500"
    },
    {
      "word": "剧",
      "rank": 6263,
      "band": 13,
      "range": "6001-6500"
    },
    {
      "word": "剫",
      "rank": 6288,
      "band": 13,
      "range": "6001-6500"
    },
    {
      "word": "剰",
      "rank": 6313,
      "band": 13,
      "range": "6001-6500"
    },
    {
      "word": "剴",
      "rank": 6338,
      "band": 13,
      "range": "6001-6500"
    },
    {
      "word": "剹",
      "rank": 6363,
      "band": 13,
      "range": "6001-6500"
    },
    {
      "word": "剽",
      "rank": 6388,
      "band": 13,
      "range": "6001-6500"
    },
    {
      "word": "劂",
      "rank": 6413,
      "band": 13,
      "range": "6001-6500"
    },
    {
      "word": "劆",
      "rank": 6438,
      "band": 13,
      "range": "6001-6500"
    },
    {
      "word": "劋",
      "rank": 6463,
      "band": 13,
      "range": "6001-6500"
    },
    {
      "word": "劏",
      "rank": 6488,
      "band": 13,
      "range": "6001-6500"
    },
    {
      "word": "劔",
      "rank": 6513,
      "band": 14,
      "range": "6501-7000"
    },
    {
      "word": "劘",
      "rank": 6538,
      "band": 14,
      "range": "6501-7000"
    },
    {
      "word": "劝",
      "rank": 6563,
      "band": 14,
      "range": "6501-7000"
    },
    {
      "word": "务",
      "rank": 6588,
      "band": 14,
      "range": "6501-7000"
    },
    {
      "word": "劦",
      "rank": 6613,
      "band": 14,
      "range": "6501-7000"
    },
    {
      "word": "努",
      "rank": 6638,
      "band": 14,
      "range": "6501-7000"
    },
    {
      "word": "劯",
      "rank": 6663,
      "band": 14,
      "range": "6501-7000"
    },
    {
      "word": "劳",
      "rank": 6688,
      "band": 14,
      "range": "6501-7000"
    },
    {
      "word": "劸",
      "rank": 6713,
      "band": 14,
      "range": "6501-7000"
    },
    {
      "word": "劼",
      "rank": 6738,
      "band": 14,
      "range": "6501-7000"
    },
    {
      "word": "勁",
      "rank": 6763,
      "band": 14,
      "range": "6501-7000"
    },
    {
      "word": "勅",
      "rank": 6788,
      "band": 14,
      "range": "6501-7000"
    },
    {
      "word": "勊",
      "rank": 6813,
      "band": 14,
      "range": "6501-7000"
    },
    {
      "word": "勎",
      "rank": 6838,
      "band": 14,
      "range": "6501-7000"
    },
    {
      "word": "勓",
      "rank": 6863,
      "band": 14,
      "range": "6501-7000"
    },
    {
      "word": "勗",
      "rank": 6888,
      "band": 14,
      "range": "6501-7000"
    },
    {
      "word": "勜",
      "rank": 6913,
      "band": 14,
      "range": "6501-7000"
    },
    {
      "word": "勠",
      "rank": 6938,
      "band": 14,
      "range": "6501-7000"
    },
    {
      "word": "勥",
      "rank": 6963,
      "band": 14,
      "range": "6501-7000"
    },
    {
      "word": "勩",
      "rank": 6988,
      "band": 14,
      "range": "6501-7000"
    },
    {
      "word": "勮",
      "rank": 7013,
      "band": 15,
      "range": "7001-7500"
    },
    {
      "word": "勲",
      "rank": 7038,
      "band": 15,
      "range": "7001-7500"
    },
    {
      "word": "勷",
      "rank": 7063,
      "band": 15,
      "range": "7001-7500"
    },
    {
      "word": "勻",
      "rank": 7088,
      "band": 15,
      "range": "7001-7500"
    },
    {
      "word": "匀",
      "rank": 7113,
      "band": 15,
      "range": "7001-7500"
    },
    {
      "word": "匄",
      "rank": 7138,
      "band": 15,
      "range": "7001-7500"
    },
    {
      "word": "匉",
      "rank": 7163,
      "band": 15,
      "range": "7001-7500"
    },
    {
      "word": "匍",
      "rank": 7188,
      "band": 15,
      "range": "7001-7500"
    },
    {
      "word": "匒",
      "rank": 7213,
      "band": 15,
      "range": "7001-7500"
    },
    {
      "word": "化",
      "rank": 7238,
      "band": 15,
      "range": "7001-7500"
    },
    {
      "word": "匛",
      "rank": 7263,
      "band": 15,
      "range": "7001-7500"
    },
    {
      "word": "匟",
      "rank": 7288,
      "band": 15,
      "range": "7001-7500"
    },
    {
      "word": "匤",
      "rank": 7313,
      "band": 15,
      "range": "7001-7500"
    },
    {
      "word": "匨",
      "rank": 7338,
      "band": 15,
      "range": "7001-7500"
    },
    {
      "word": "匭",
      "rank": 7363,
      "band": 15,
      "range": "7001-7500"
    },
    {
      "word": "匱",
      "rank": 7388,
      "band": 15,
      "range": "7001-7500"
    },
    {
      "word": "匶",
      "rank": 7413,
      "band": 15,
      "range": "7001-7500"
    },
    {
      "word": "区",
      "rank": 7438,
      "band": 15,
      "range": "7001-7500"
    },
    {
      "word": "匿",
      "rank": 7463,
      "band": 15,
      "range": "7001-7500"
    },
    {
      "word": "千",
      "rank": 7488,
      "band": 15,
      "range": "7001-7500"
    },
    {
      "word": "午",
      "rank": 7513,
      "band": 16,
      "range": "7501-8000"
    },
    {
      "word": "卌",
      "rank": 7538,
      "band": 16,
      "range": "7501-8000"
    },
    {
      "word": "卑",
      "rank": 7563,
      "band": 16,
      "range": "7501-8000"
    },
    {
      "word": "单",
      "rank": 7588,
      "band": 16,
      "range": "7501-8000"
    },
    {
      "word": "博",
      "rank": 7613,
      "band": 16,
      "range": "7501-8000"
    },
    {
      "word": "卞",
      "rank": 7638,
      "band": 16,
      "range": "7501-8000"
    },
    {
      "word": "卣",
      "rank": 7663,
      "band": 16,
      "range": "7501-8000"
    },
    {
      "word": "卧",
      "rank": 7688,
      "band": 16,
      "range": "7501-8000"
    },
    {
      "word": "卬",
      "rank": 7713,
      "band": 16,
      "range": "7501-8000"
    },
    {
      "word": "印",
      "rank": 7738,
      "band": 16,
      "range": "7501-8000"
    },
    {
      "word": "卵",
      "rank": 7763,
      "band": 16,
      "range": "7501-8000"
    },
    {
      "word": "卹",
      "rank": 7788,
      "band": 16,
      "range": "7501-8000"
    },
    {
      "word": "卾",
      "rank": 7813,
      "band": 16,
      "range": "7501-8000"
    },
    {
      "word": "厂",
      "rank": 7838,
      "band": 16,
      "range": "7501-8000"
    },
    {
      "word": "厇",
      "rank": 7863,
      "band": 16,
      "range": "7501-8000"
    },
    {
      "word": "压",
      "rank": 7888,
      "band": 16,
      "range": "7501-8000"
    },
    {
      "word": "厐",
      "rank": 7913,
      "band": 16,
      "range": "7501-8000"
    },
    {
      "word": "厔",
      "rank": 7938,
      "band": 16,
      "range": "7501-8000"
    },
    {
      "word": "厙",
      "rank": 7963,
      "band": 16,
      "range": "7501-8000"
    },
    {
      "word": "厝",
      "rank": 7988,
      "band": 16,
      "range": "7501-8000"
    },
    {
      "word": "厢",
      "rank": 8013,
      "band": 17,
      "range": "8001-8500"
    },
    {
      "word": "厦",
      "rank": 8038,
      "band": 17,
      "range": "8001-8500"
    },
    {
      "word": "厫",
      "rank": 8063,
      "band": 17,
      "range": "8001-8500"
    },
    {
      "word": "厯",
      "rank": 8088,
      "band": 17,
      "range": "8001-8500"
    },
    {
      "word": "厴",
      "rank": 8113,
      "band": 17,
      "range": "8001-8500"
    },
    {
      "word": "厸",
      "rank": 8138,
      "band": 17,
      "range": "8001-8500"
    },
    {
      "word": "厽",
      "rank": 8163,
      "band": 17,
      "range": "8001-8500"
    },
    {
      "word": "叁",
      "rank": 8188,
      "band": 17,
      "range": "8001-8500"
    },
    {
      "word": "叆",
      "rank": 8213,
      "band": 17,
      "range": "8001-8500"
    },
    {
      "word": "及",
      "rank": 8238,
      "band": 17,
      "range": "8001-8500"
    },
    {
      "word": "叏",
      "rank": 8263,
      "band": 17,
      "range": "8001-8500"
    },
    {
      "word": "叓",
      "rank": 8288,
      "band": 17,
      "range": "8001-8500"
    },
    {
      "word": "变",
      "rank": 8313,
      "band": 17,
      "range": "8001-8500"
    },
    {
      "word": "叜",
      "rank": 8338,
      "band": 17,
      "range": "8001-8500"
    },
    {
      "word": "叡",
      "rank": 8363,
      "band": 17,
      "range": "8001-8500"
    },
    {
      "word": "句",
      "rank": 8388,
      "band": 17,
      "range": "8001-8500"
    },
    {
      "word": "只",
      "rank": 8413,
      "band": 17,
      "range": "8001-8500"
    },
    {
      "word": "叮",
      "rank": 8438,
      "band": 17,
      "range": "8001-8500"
    },
    {
      "word": "右",
      "rank": 8463,
      "band": 17,
      "range": "8001-8500"
    },
    {
      "word": "号",
      "rank": 8488,
      "band": 17,
      "range": "8001-8500"
    },
    {
      "word": "叼",
      "rank": 8513,
      "band": 18,
      "range": "8501-9000"
    },
    {
      "word": "吀",
      "rank": 8538,
      "band": 18,
      "range": "8501-9000"
    },
    {
      "word": "吅",
      "rank": 8563,
      "band": 18,
      "range": "8501-9000"
    },
    {
      "word": "吉",
      "rank": 8588,
      "band": 18,
      "range": "8501-9000"
    },
    {
      "word": "后",
      "rank": 8613,
      "band": 18,
      "range": "8501-9000"
    },
    {
      "word": "吒",
      "rank": 8638,
      "band": 18,
      "range": "8501-9000"
    },
    {
      "word": "吗",
      "rank": 8663,
      "band": 18,
      "range": "8501-9000"
    },
    {
      "word": "君",
      "rank": 8688,
      "band": 18,
      "range": "8501-9000"
    },
    {
      "word": "吠",
      "rank": 8713,
      "band": 18,
      "range": "8501-9000"
    },
    {
      "word": "吤",
      "rank": 8738,
      "band": 18,
      "range": "8501-9000"
    },
    {
      "word": "吩",
      "rank": 8763,
      "band": 18,
      "range": "8501-9000"
    },
    {
      "word": "吭",
      "rank": 8788,
      "band": 18,
      "range": "8501-9000"
    },
    {
      "word": "吲",
      "rank": 8813,
      "band": 18,
      "range": "8501-9000"
    },
    {
      "word": "吶",
      "rank": 8838,
      "band": 18,
      "range": "8501-9000"
    },
    {
      "word": "吻",
      "rank": 8863,
      "band": 18,
      "range": "8501-9000"
    },
    {
      "word": "吿",
      "rank": 8888,
      "band": 18,
      "range": "8501-9000"
    },
    {
      "word": "呄",
      "rank": 8913,
      "band": 18,
      "range": "8501-9000"
    },
    {
      "word": "呈",
      "rank": 8938,
      "band": 18,
      "range": "8501-9000"
    },
    {
      "word": "呍",
      "rank": 8963,
      "band": 18,
      "range": "8501-9000"
    },
    {
      "word": "呑",
      "rank": 8988,
      "band": 18,
      "range": "8501-9000"
    },
    {
      "word": "呖",
      "rank": 9013,
      "band": 19,
      "range": "9001-9500"
    },
    {
      "word": "呚",
      "rank": 9038,
      "band": 19,
      "range": "9001-9500"
    },
    {
      "word": "呟",
      "rank": 9063,
      "band": 19,
      "range": "9001-9500"
    },
    {
      "word": "呣",
      "rank": 9088,
      "band": 19,
      "range": "9001-9500"
    },
    {
      "word": "周",
      "rank": 9113,
      "band": 19,
      "range": "9001-9500"
    },
    {
      "word": "呬",
      "rank": 9138,
      "band": 19,
      "range": "9001-9500"
    },
    {
      "word": "呱",
      "rank": 9163,
      "band": 19,
      "range": "9001-9500"
    },
    {
      "word": "呵",
      "rank": 9188,
      "band": 19,
      "range": "9001-9500"
    },
    {
      "word": "呺",
      "rank": 9213,
      "band": 19,
      "range": "9001-9500"
    },
    {
      "word": "呾",
      "rank": 9238,
      "band": 19,
      "range": "9001-9500"
    },
    {
      "word": "咃",
      "rank": 9263,
      "band": 19,
      "range": "9001-9500"
    },
    {
      "word": "咇",
      "rank": 9288,
      "band": 19,
      "range": "9001-9500"
    },
    {
      "word": "和",
      "rank": 9313,
      "band": 19,
      "range": "9001-9500"
    },
    {
      "word": "咐",
      "rank": 9338,
      "band": 19,
      "range": "9001-9500"
    },
    {
      "word": "咕",
      "rank": 9363,
      "band": 19,
      "range": "9001-9500"
    },
    {
      "word": "咙",
      "rank": 9388,
      "band": 19,
      "range": "9001-9500"
    },
    {
      "word": "咞",
      "rank": 9413,
      "band": 19,
      "range": "9001-9500"
    },
    {
      "word": "咢",
      "rank": 9438,
      "band": 19,
      "range": "9001-9500"
    },
    {
      "word": "咧",
      "rank": 9463,
      "band": 19,
      "range": "9001-9500"
    },
    {
      "word": "咫",
      "rank": 9488,
      "band": 19,
      "range": "9001-9500"
    },
    {
      "word": "咰",
      "rank": 9513,
      "band": 20,
      "range": "9501-10000"
    },
    {
      "word": "咴",
      "rank": 9538,
      "band": 20,
      "range": "9501-10000"
    },
    {
      "word": "咹",
      "rank": 9563,
      "band": 20,
      "range": "9501-10000"
    },
    {
      "word": "咽",
      "rank": 9588,
      "band": 20,
      "range": "9501-10000"
    },
    {
      "word": "哂",
      "rank": 9613,
      "band": 20,
      "range": "9501-10000"
    },
    {
      "word": "哆",
      "rank": 9638,
      "band": 20,
      "range": "9501-10000"
    },
    {
      "word": "哋",
      "rank": 9663,
      "band": 20,
      "range": "9501-10000"
    },
    {
      "word": "哏",
      "rank": 9688,
      "band": 20,
      "range": "9501-10000"
    },
    {
      "word": "哔",
      "rank": 9713,
      "band": 20,
      "range": "9501-10000"
    },
    {
      "word": "哘",
      "rank": 9738,
      "band": 20,
      "range": "9501-10000"
    },
    {
      "word": "哝",
      "rank": 9763,
      "band": 20,
      "range": "9501-10000"
    },
    {
      "word": "員",
      "rank": 9788,
      "band": 20,
      "range": "9501-10000"
    },
    {
      "word": "哦",
      "rank": 9813,
      "band": 20,
      "range": "9501-10000"
    },
    {
      "word": "哪",
      "rank": 9838,
      "band": 20,
      "range": "9501-10000"
    },
    {
      "word": "哯",
      "rank": 9863,
      "band": 20,
      "range": "9501-10000"
    },
    {
      "word": "哳",
      "rank": 9888,
      "band": 20,
      "range": "9501-10000"
    },
    {
      "word": "哸",
      "rank": 9913,
      "band": 20,
      "range": "9501-10000"
    },
    {
      "word": "哼",
      "rank": 9938,
      "band": 20,
      "range": "9501-10000"
    },
    {
      "word": "唁",
      "rank": 9963,
      "band": 20,
      "range": "9501-10000"
    },
    {
      "word": "唅",
      "rank": 9988,
      "band": 20,
      "range": "9501-10000"
    }
  ]
}
