{
  "language": "Korean (Hanja)",
  "code": "ko-hanja",
  "mode": "character",
  "unitLabel": "characters",
  "maxRank": 10000,
  "bandSize": 500,
  "bands": [
    { "index": 1, "range": "1-500", "size": 500 },
    { "index": 2, "range": "501-1000", "size": 500 },
    { "index": 3, "range": "1001-1500", "size": 500 },
    { "index": 4, "range": "1501-2000", "size": 500 },
    { "index": 5, "range": "2001-2500", "size": 500 },
    { "index": 6, "range": "2501-3000", "size": 500 },
    { "index": 7, "range": "3001-3500", "size": 500 },
    { "index": 8, "range": "3501-4000", "size": 500 },
    { "index": 9, "range": "4001-4500", "size": 500 },
    { "index": 10, "range": "4501-5000", "size": 500 },
    { "index": 11, "range": "5001-5500", "size": 500 },
    { "index": 12, "range": "5501-6000", "size": 500 },
    { "index": 13, "range": "6001-6500", "size": 500 },
    { "index": 14, "range": "6501-7000", "size": 500 },
    { "index": 15, "range": "7001-7500", "size": 500 },
    { "index": 16, "range": "7501-8000", "size": 500 },
    { "index": 17, "range": "8001-8500", "size": 500 },
    { "index": 18, "range": "8501-9000", "size": 500 },
    { "index": 19, "range": "9001-9500", "size": 500 },
    { "index": 20, "range": "9501-10000", "size": 500 }
  ],
  "words": [
    { "word": "人", "rank": 1, "band": 1, "range": "1-500" },
    { "word": "大", "rank": 2, "band": 1, "range": "1-500" },
    { "word": "中", "rank": 3, "band": 1, "range": "1-500" },
    { "word": "國", "rank": 4, "band": 1, "range": "1-500" },
    { "word": "日", "rank": 5, "band": 1, "range": "1-500" },

    { "word": "本", "rank": 520, "band": 2, "range": "501-1000" },
    { "word": "年", "rank": 610, "band": 2, "range": "501-1000" },
    { "word": "月", "rank": 740, "band": 2, "range": "501-1000" },
    { "word": "時", "rank": 860, "band": 2, "range": "501-1000" },
    { "word": "上", "rank": 990, "band": 2, "range": "501-1000" },

    { "word": "下", "rank": 1050, "band": 3, "range": "1001-1500" },
    { "word": "生", "rank": 1120, "band": 3, "range": "1001-1500" },
    { "word": "學", "rank": 1240, "band": 3, "range": "1001-1500" },
    { "word": "校", "rank": 1360, "band": 3, "range": "1001-1500" },
    { "word": "山", "rank": 1480, "band": 3, "range": "1001-1500" },

    { "word": "川", "rank": 1520, "band": 4, "range": "1501-2000" },
    { "word": "水", "rank": 1630, "band": 4, "range": "1501-2000" },
    { "word": "火", "rank": 1740, "band": 4, "range": "1501-2000" },
    { "word": "木", "rank": 1860, "band": 4, "range": "1501-2000" },
    { "word": "金", "rank": 1980, "band": 4, "range": "1501-2000" },

    { "word": "土", "rank": 2050, "band": 5, "range": "2001-2500" },
    { "word": "天", "rank": 2140, "band": 5, "range": "2001-2500" },
    { "word": "地", "rank": 2260, "band": 5, "range": "2001-2500" },
    { "word": "心", "rank": 2380, "band": 5, "range": "2001-2500" },
    { "word": "手", "rank": 2490, "band": 5, "range": "2001-2500" },

    { "word": "目", "rank": 2550, "band": 6, "range": "2501-3000" },
    { "word": "耳", "rank": 2660, "band": 6, "range": "2501-3000" },
    { "word": "口", "rank": 2740, "band": 6, "range": "2501-3000" },
    { "word": "力", "rank": 2860, "band": 6, "range": "2501-3000" },
    { "word": "先", "rank": 2970, "band": 6, "range": "2501-3000" },

    { "word": "友", "rank": 3050, "band": 7, "range": "3001-3500" },
    { "word": "名", "rank": 3160, "band": 7, "range": "3001-3500" },
    { "word": "文", "rank": 3260, "band": 7, "range": "3001-3500" },
    { "word": "字", "rank": 3380, "band": 7, "range": "3001-3500" },
    { "word": "方", "rank": 3490, "band": 7, "range": "3001-3500" },

    { "word": "海", "rank": 3560, "band": 8, "range": "3501-4000" },
    { "word": "空", "rank": 3660, "band": 8, "range": "3501-4000" },
    { "word": "氣", "rank": 3760, "band": 8, "range": "3501-4000" },
    { "word": "電", "rank": 3880, "band": 8, "range": "3501-4000" },
    { "word": "話", "rank": 3990, "band": 8, "range": "3501-4000" },

    { "word": "車", "rank": 4050, "band": 9, "range": "4001-4500" },
    { "word": "道", "rank": 4160, "band": 9, "range": "4001-4500" },
    { "word": "市", "rank": 4270, "band": 9, "range": "4001-4500" },
    { "word": "場", "rank": 4380, "band": 9, "range": "4001-4500" },
    { "word": "會", "rank": 4490, "band": 9, "range": "4001-4500" },

    { "word": "社", "rank": 4560, "band": 10, "range": "4501-5000" },
    { "word": "家", "rank": 4660, "band": 10, "range": "4501-5000" },
    { "word": "食", "rank": 4760, "band": 10, "range": "4501-5000" },
    { "word": "飲", "rank": 4880, "band": 10, "range": "4501-5000" },
    { "word": "物", "rank": 4990, "band": 10, "range": "4501-5000" },

    { "word": "言", "rank": 5050, "band": 11, "range": "5001-5500" },
    { "word": "語", "rank": 5160, "band": 11, "range": "5001-5500" },
    { "word": "書", "rank": 5260, "band": 11, "range": "5001-5500" },
    { "word": "讀", "rank": 5380, "band": 11, "range": "5001-5500" },
    { "word": "新", "rank": 5490, "band": 11, "range": "5001-5500" },

    { "word": "古", "rank": 5560, "band": 12, "range": "5501-6000" },
    { "word": "長", "rank": 5660, "band": 12, "range": "5501-6000" },
    { "word": "短", "rank": 5760, "band": 12, "range": "5501-6000" },
    { "word": "高", "rank": 5860, "band": 12, "range": "5501-6000" },
    { "word": "低", "rank": 5990, "band": 12, "range": "5501-6000" },

    { "word": "明", "rank": 6060, "band": 13, "range": "6001-6500" },
    { "word": "暗", "rank": 6160, "band": 13, "range": "6001-6500" },
    { "word": "白", "rank": 6260, "band": 13, "range": "6001-6500" },
    { "word": "黑", "rank": 6380, "band": 13, "range": "6001-6500" },
    { "word": "赤", "rank": 6490, "band": 13, "range": "6001-6500" },

    { "word": "青", "rank": 6550, "band": 14, "range": "6501-7000" },
    { "word": "黃", "rank": 6660, "band": 14, "range": "6501-7000" },
    { "word": "春", "rank": 6760, "band": 14, "range": "6501-7000" },
    { "word": "夏", "rank": 6880, "band": 14, "range": "6501-7000" },
    { "word": "秋", "rank": 6990, "band": 14, "range": "6501-7000" },

    { "word": "冬", "rank": 7050, "band": 15, "range": "7001-7500" },
    { "word": "北", "rank": 7160, "band": 15, "range": "7001-7500" },
    { "word": "南", "rank": 7260, "band": 15, "range": "7001-7500" },
    { "word": "東", "rank": 7380, "band": 15, "range": "7001-7500" },
    { "word": "西", "rank": 7490, "band": 15, "range": "7001-7500" },

    { "word": "風", "rank": 7560, "band": 16, "range": "7501-8000" },
    { "word": "雨", "rank": 7660, "band": 16, "range": "7501-8000" },
    { "word": "雪", "rank": 7760, "band": 16, "range": "7501-8000" },
    { "word": "星", "rank": 7880, "band": 16, "range": "7501-8000" },
    { "word": "光", "rank": 7990, "band": 16, "range": "7501-8000" },

    { "word": "音", "rank": 8060, "band": 17, "range": "8001-8500" },
    { "word": "樂", "rank": 8160, "band": 17, "range": "8001-8500" },
    { "word": "旅", "rank": 8260, "band": 17, "range": "8001-8500" },
    { "word": "近", "rank": 8380, "band": 17, "range": "8001-8500" },
    { "word": "遠", "rank": 8490, "band": 17, "range": "8001-8500" },

    { "word": "強", "rank": 8560, "band": 18, "range": "8501-9000" },
    { "word": "弱", "rank": 8660, "band": 18, "range": "8501-9000" },
    { "word": "多", "rank": 8760, "band": 18, "range": "8501-9000" },
    { "word": "少", "rank": 8880, "band": 18, "range": "8501-9000" },
    { "word": "安", "rank": 8990, "band": 18, "range": "8501-9000" },

    { "word": "危", "rank": 9060, "band": 19, "range": "9001-9500" },
    { "word": "早", "rank": 9160, "band": 19, "range": "9001-9500" },
    { "word": "遲", "rank": 9260, "band": 19, "range": "9001-9500" },
    { "word": "美", "rank": 9380, "band": 19, "range": "9001-9500" },
    { "word": "重", "rank": 9490, "band": 19, "range": "9001-9500" },

    { "word": "輕", "rank": 9560, "band": 20, "range": "9501-10000" },
    { "word": "有", "rank": 9660, "band": 20, "range": "9501-10000" },
    { "word": "無", "rank": 9760, "band": 20, "range": "9501-10000" },
    { "word": "正", "rank": 9880, "band": 20, "range": "9501-10000" },
    { "word": "誤", "rank": 9990, "band": 20, "range": "9501-10000" }
  ]
}
